email_cleaning_service/__init__.py
email_cleaning_service/config.py
email_cleaning_service/control.py
email_cleaning_service/data_model/__init__.py
email_cleaning_service/data_model/data.py
email_cleaning_service/data_model/pipelining.py
email_cleaning_service/services/__init__.py
email_cleaning_service/services/azure_service.py
email_cleaning_service/services/segmenting_service.py
email_cleaning_service/services/training_service.py
email_cleaning_service/utils/__init__.py
email_cleaning_service/utils/custom_exceptions.py
email_cleaning_service/utils/data_manipulation.py
email_cleaning_service/utils/delete_run.py
email_cleaning_service/utils/initialize_mlflow.py
email_cleaning_service/utils/metrics.py
email_cleaning_service/utils/request_classes.py
tests/__init__.py
tests/test_control.py
email_cleaning_service-1.0.0.dist-info/LICENSE
email_cleaning_service-1.0.0.dist-info/METADATA
email_cleaning_service-1.0.0.dist-info/WHEEL
email_cleaning_service-1.0.0.dist-info/top_level.txt
email_cleaning_service-1.0.0.dist-info/RECORD
